pyinstaller_hooks/__init__.py
pyinstaller_hooks/hook-pylibimport.py
pyinstaller_hooks/__pycache__/hook-pylibimport.cpython-36.pyc
pylibimport/__init__.py
pylibimport/__meta__.py
pylibimport/download.py
pylibimport/finder_loader.py
pylibimport/get_versions.py
pylibimport/install.py
pylibimport/lib_import.py
pylibimport/utils.py
pylibimport/__pycache__/__init__.cpython-34.pyc
pylibimport/__pycache__/__init__.cpython-36.pyc
pylibimport/__pycache__/__init__.cpython-38.pyc
pylibimport/__pycache__/__meta__.cpython-34.pyc
pylibimport/__pycache__/__meta__.cpython-36.pyc
pylibimport/__pycache__/__meta__.cpython-38.pyc
pylibimport/__pycache__/download.cpython-34.pyc
pylibimport/__pycache__/download.cpython-36.pyc
pylibimport/__pycache__/download.cpython-38.pyc
pylibimport/__pycache__/finder_loader.cpython-38.pyc
pylibimport/__pycache__/get_versions.cpython-34.pyc
pylibimport/__pycache__/get_versions.cpython-36.pyc
pylibimport/__pycache__/get_versions.cpython-38.pyc
pylibimport/__pycache__/install.cpython-34.pyc
pylibimport/__pycache__/install.cpython-36.pyc
pylibimport/__pycache__/install.cpython-38.pyc
pylibimport/__pycache__/lib_import.cpython-34.pyc
pylibimport/__pycache__/lib_import.cpython-36.pyc
pylibimport/__pycache__/lib_import.cpython-38.pyc
pylibimport/__pycache__/utils.cpython-34.pyc
pylibimport/__pycache__/utils.cpython-36.pyc
pylibimport/__pycache__/utils.cpython-38.pyc
pylibimport/pip_utils/__init__.py
pylibimport/pip_utils/binary.py
pylibimport/pip_utils/main_func.py
pylibimport/pip_utils/utils.py
pylibimport/pip_utils/__pycache__/__init__.cpython-36.pyc
pylibimport/pip_utils/__pycache__/__init__.cpython-38.pyc
pylibimport/pip_utils/__pycache__/binary.cpython-36.pyc
pylibimport/pip_utils/__pycache__/binary.cpython-38.pyc
pylibimport/pip_utils/__pycache__/fix_pip_subprocess.cpython-36.pyc
pylibimport/pip_utils/__pycache__/fix_pip_subprocess.cpython-38.pyc
pylibimport/pip_utils/__pycache__/main_func.cpython-36.pyc
pylibimport-1.9.2.dist-info/LICENSE
pylibimport-1.9.2.dist-info/METADATA
pylibimport-1.9.2.dist-info/WHEEL
pylibimport-1.9.2.dist-info/top_level.txt
pylibimport-1.9.2.dist-info/RECORD
