Metadata-Version: 2.1
Name: pylibimport
Version: 1.9.2
Summary: Python utility for importing packages with the same name, but different version.
Home-page: https://github.com/justengel/pylibimport
Author: Justin Engel
Author-email: jtengel08@gmail.com
License: MIT
Download-URL: https://github.com/justengel/pylibimport/archive/v1.9.2.tar.gz
Keywords: python version import libimport library version_import
Platform: any
Classifier: Programming Language :: Python
Classifier: Programming Language :: Python :: 3
Classifier: Operating System :: OS Independent
Requires-Dist: pylibimp (>=1.0.1)
Requires-Dist: packaging (>=20.3)
Requires-Dist: requests (>=2.18.2)
Requires-Dist: light-process (>=0.0.2)
Requires-Dist: package-parser (>=1.0.2)
